{
  "result": {
    "params": {
      "Ncells": 3000,
      "ws": [
        0.0003,
        0.001,
        0.003,
        0.01,
        0.03,
        0.1,
        0.3,
        1.0
      ],
      "seeds": [
        0,
        1,
        2,
        3,
        4,
        5
      ]
    },
    "rows": [
      {
        "w": 0.0003,
        "founders": 1.5,
        "relatedness": 0.806
      },
      {
        "w": 0.001,
        "founders": 3.5,
        "relatedness": 0.406
      },
      {
        "w": 0.003,
        "founders": 9.8,
        "relatedness": 0.116
      },
      {
        "w": 0.01,
        "founders": 30.5,
        "relatedness": 0.033
      },
      {
        "w": 0.03,
        "founders": 88.3,
        "relatedness": 0.012
      },
      {
        "w": 0.1,
        "founders": 304.8,
        "relatedness": 0.004
      },
      {
        "w": 0.3,
        "founders": 895.2,
        "relatedness": 0.001
      },
      {
        "w": 1.0,
        "founders": 3000.0,
        "relatedness": 0.001
      }
    ],
    "narrow": {
      "w": 0.0003,
      "founders": 1.5,
      "relatedness": 0.806
    },
    "wide": {
      "w": 1.0,
      "founders": 3000.0,
      "relatedness": 0.001
    },
    "relatedness_monotone_in_width": true
  },
  "atlas": [
    {
      "experiment": "e041 field bottleneck (neck geometry -> founder number -> clonality)",
      "tier": "measured",
      "put_in": "a tagged body (distinct founder identities) + a pinch neck of width w; the daughter regrows from whoever passed the neck. NO narrow->clonal put in",
      "emerged": [
        "neck width -> (founders, relatedness): [(0.0003, 1.5, 0.806), (0.001, 3.5, 0.406), (0.003, 9.8, 0.116), (0.01, 30.5, 0.033), (0.03, 88.3, 0.012), (0.1, 304.8, 0.004), (0.3, 895.2, 0.001), (1.0, 3000.0, 0.001)]",
        "narrow neck: 1.5 founders, relatedness 0.806 (clonal); wide neck: 3000.0 founders, relatedness 0.001 (mixed)"
      ],
      "surprises": [
        "the single-cell bottleneck of the major transition is not an abstract rule -- it is set by the WIDTH of the dividing neck (geometry)"
      ],
      "persistence": "relatedness decreases monotonically as the neck widens (few founders -> clonal, many -> mixed)",
      "measured_numbers": {
        "rows": [
          {
            "w": 0.0003,
            "founders": 1.5,
            "relatedness": 0.806
          },
          {
            "w": 0.001,
            "founders": 3.5,
            "relatedness": 0.406
          },
          {
            "w": 0.003,
            "founders": 9.8,
            "relatedness": 0.116
          },
          {
            "w": 0.01,
            "founders": 30.5,
            "relatedness": 0.033
          },
          {
            "w": 0.03,
            "founders": 88.3,
            "relatedness": 0.012
          },
          {
            "w": 0.1,
            "founders": 304.8,
            "relatedness": 0.004
          },
          {
            "w": 0.3,
            "founders": 895.2,
            "relatedness": 0.001
          },
          {
            "w": 1.0,
            "founders": 3000.0,
            "relatedness": 0.001
          }
        ],
        "narrow": {
          "w": 0.0003,
          "founders": 1.5,
          "relatedness": 0.806
        },
        "wide": {
          "w": 1.0,
          "founders": 3000.0,
          "relatedness": 0.001
        }
      },
      "not_scripted_check": "the neck-width -> relatedness relationship is measured, not imposed",
      "claim_tier": "measured (founder count + relatedness vs neck width) ; interpretive (the bottleneck emerges from the pinch geometry) ; analogy (clonality / relatedness)",
      "floors": [
        "S: a GEOMETRIC SAMPLING model (a neck strip over a tagged body), NOT a continuum field",
        "the founder->clonal regrowth is imposed; 'clonal / relatedness / individual' is analogy",
        "\u540c\u3058\u6570\u5b66\u2260\u540c\u3058\u3082\u306e: this abstracts the pinch geometry; it is not a faithful field PDE"
      ]
    }
  ]
}